atlas/__init__.py
atlas/__main__.py
atlas/classification/__init__.py
atlas/classification/classifier.py
atlas/cli/__init__.py
atlas/cli/main.py
atlas/config/__init__.py
atlas/config/settings.py
atlas/history/__init__.py
atlas/history/store.py
atlas/io/__init__.py
atlas/io/json_io.py
atlas/normalization/__init__.py
atlas/normalization/normalizer.py
atlas/orchestrator/__init__.py
atlas/orchestrator/pipeline.py
atlas/parsing/__init__.py
atlas/parsing/log_parser.py
atlas/rca/__init__.py
atlas/rca/engine.py
atlas/recommendations/__init__.py
atlas/recommendations/actions.py
atlas/schemas/__init__.py
atlas/schemas/incident.py
atlas/similarity/__init__.py
atlas/similarity/matcher.py
atlas/utils/__init__.py
atlas/utils/time.py
atlas_v2/__init__.py
atlas_v2/actions/__init__.py
atlas_v2/actions/executor.py
atlas_v2/audit/__init__.py
atlas_v2/audit/trail.py
atlas_v2/integration/__init__.py
atlas_v2/integration/controller.py
atlas_v2/integration/wiring.py
atlas_v2/priority/__init__.py
atlas_v2/priority/frequency.py
atlas_v2/priority/scorer.py
atlas_v2/priority/weights.py
atlas_v2/rules/__init__.py
atlas_v2/rules/definitions.py
atlas_v2/rules/engine.py
atlas_v2/rules/rules.py
atlas_v2/schemas/__init__.py
atlas_v2/schemas/decision.py
atlas_v2/state/__init__.py
atlas_v2/state/store.py
atlas_v2/tests/test_frequency_determinism.py
atlas_v2/tests/test_integration.py
atlas_v2/tests/test_priority.py
atlas_v2/tests/test_priority_edge.py
atlas_v2/tests/test_rules.py
atlas_v2/tests/test_workflow.py
atlas_v2/workflow/__init__.py
atlas_v2/workflow/definitions.py
atlas_v2/workflow/engine.py
atlas_v2/workflow/flows.py
atlas_incident-0.1.2.dist-info/METADATA
atlas_incident-0.1.2.dist-info/WHEEL
atlas_incident-0.1.2.dist-info/entry_points.txt
atlas_incident-0.1.2.dist-info/top_level.txt
atlas_incident-0.1.2.dist-info/RECORD
