Metadata-Version: 2.4
Name: atlas-incident
Version: 0.1.2
Summary: Deterministic, rule-based incident analysis and RCA system
Author: Nihal
License-Expression: MIT
Requires-Python: >=3.10
